{"trial_id": "05", "hyperparameters": {"space": [{"class_name": "Float", "config": {"name": "bn_momentum", "default": 0.1, "conditions": [], "min_value": 0.1, "max_value": 0.9, "step": 0.1, "sampling": "linear"}}, {"class_name": "Int", "config": {"name": "units", "default": null, "conditions": [], "min_value": 8, "max_value": 64, "step": 2, "sampling": "linear"}}, {"class_name": "Choice", "config": {"name": "activation", "default": "relu", "conditions": [], "values": ["relu", "tanh"], "ordered": false}}, {"class_name": "Float", "config": {"name": "l1", "default": 0.0, "conditions": [], "min_value": 0.0, "max_value": 0.1, "step": 0.01, "sampling": "linear"}}, {"class_name": "Boolean", "config": {"name": "dropout", "default": false, "conditions": []}}, {"class_name": "Int", "config": {"name": "num_layers", "default": null, "conditions": [], "min_value": 1, "max_value": 2, "step": 1, "sampling": "linear"}}, {"class_name": "Int", "config": {"name": "units_1", "default": null, "conditions": [], "min_value": 4, "max_value": 32, "step": 2, "sampling": "linear"}}, {"class_name": "Choice", "config": {"name": "activation_0", "default": "relu", "conditions": [], "values": ["relu", "tanh", "LeakyReLU"], "ordered": false}}, {"class_name": "Float", "config": {"name": "lr", "default": 0.0001, "conditions": [], "min_value": 0.0001, "max_value": 0.01, "step": null, "sampling": "log"}}, {"class_name": "Float", "config": {"name": "momentum", "default": 0.0, "conditions": [], "min_value": 0.0, "max_value": 0.9, "step": 0.1, "sampling": "linear"}}, {"class_name": "Choice", "config": {"name": "optimizer", "default": "adam", "conditions": [], "values": ["adam", "sgd", "rmsprop"], "ordered": false}}, {"class_name": "Int", "config": {"name": "units_2", "default": null, "conditions": [], "min_value": 4, "max_value": 32, "step": 2, "sampling": "linear"}}, {"class_name": "Choice", "config": {"name": "activation_1", "default": "relu", "conditions": [], "values": ["relu", "tanh", "LeakyReLU"], "ordered": false}}, {"class_name": "Float", "config": {"name": "dropout_rate", "default": 0.1, "conditions": [], "min_value": 0.1, "max_value": 0.5, "step": 0.1, "sampling": "linear"}}], "values": {"bn_momentum": 0.6, "units": 42, "activation": "tanh", "l1": 0.01, "dropout": true, "num_layers": 2, "units_1": 8, "activation_0": "tanh", "lr": 0.0001787125964217817, "momentum": 0.0, "optimizer": "sgd", "units_2": 30, "activation_1": "LeakyReLU", "dropout_rate": 0.5}}, "metrics": {"metrics": {"loss": {"direction": "min", "observations": [{"value": [16.60155423482259], "step": 43}]}, "mae": {"direction": "min", "observations": [{"value": [3.263146718343099], "step": 43}]}, "val_loss": {"direction": "min", "observations": [{"value": [10.944008827209473], "step": 43}]}, "val_mae": {"direction": "min", "observations": [{"value": [2.6599058310190835], "step": 43}]}, "learning_rate": {"direction": "min", "observations": [{"value": [3.574251968530007e-05], "step": 43}]}}}, "score": 10.944008827209473, "best_step": 43, "status": "COMPLETED", "message": null}